<?xml version="1.0" encoding="UTF-8" standalone="no"?><api xmlns:xsi="http://www.w3.org/2001/XMLSchema-instance" ekapiName="ADM_ALERTE" xsi:schemaLocation="http://www.w3.org/2001/XMLSchema cascade.xsd"><ekapiNameBr>ADM_ALERTS</ekapiNameBr><ekapiType>MDW</ekapiType><stdFlag>SPEC</stdFlag><label>Gestion des alertes</label><labelBr>Alerts management</labelBr><comment>Gestion des alertes</comment><commentBr>Alerts management</commentBr><statusCode>ETUD</statusCode><utilizationCode>I</utilizationCode><processFlag>N</processFlag><level>0</level><domainCode>workflow</domainCode><validationFlag>O</validationFlag><noVersionEkip>7.2</noVersionEkip><lotFlag>O</lotFlag><alimList><alim id="1"><parameterName>ID_ALERTDOSADM</parameterName><useEkapiName>TALERTDOSADM</useEkapiName><useParameterName>ID_ALERTDOSADM</useParameterName><comment>Idantifiant de la table ALERTDOSADM</comment></alim><alim id="2"><parameterName>DATE_ECHEANCE</parameterName><useEkapiName>TALERTDOSADM</useEkapiName><useParameterName>DATE_ECHEANCE</useParameterName><comment>Date de l'echeance de l'alerte</comment></alim><alim id="3"><parameterName>CODE_STAUT</parameterName><useEkapiName>TALERTDOSADM</useEkapiName><useParameterName>CODE_STATUT</useParameterName><comment>Code de statut de l'alerte</comment></alim></alimList><listList><list id="1"><useEkapiName>TALERTDOSADM</useEkapiName><comment>API privée</comment></list></listList></api>